social_tags
